genetic_algorithms/__init__.py
genetic_algorithms/function_optimization.py
genetic_algorithms/knapsack.py
genetic_algorithms/map_coloring.py
genetic_algorithms/n_queens.py
genetic_algorithms/tsp.py
genetic_algorithms_suite-0.2.0.dist-info/METADATA
genetic_algorithms_suite-0.2.0.dist-info/WHEEL
genetic_algorithms_suite-0.2.0.dist-info/top_level.txt
genetic_algorithms_suite-0.2.0.dist-info/RECORD
