Metadata-Version: 2.4
Name: genetic-algorithms-suite
Version: 0.2.0
Summary: A collection of genetic algorithm implementations for common optimization problems.
Author-email: Your Name <your.email@example.com>
Project-URL: Homepage, https://github.com/yourusername/genetic-algorithms-suite
Requires-Python: >=3.8
Requires-Dist: numpy>=1.21
